jax_chmc/__init__.py
jax_chmc/__main__.py
jax_chmc/kernels.py
jax_chmc/mvn.py
jax_chmc/rattle.py
jax_chmc-0.0.7.dist-info/METADATA
jax_chmc-0.0.7.dist-info/WHEEL
jax_chmc-0.0.7.dist-info/licenses/LICENSE
jax_chmc-0.0.7.dist-info/RECORD
