Metadata-Version: 2.1
Name: jax_chmc
Version: 0.0.7
Summary: An implementation of a family of MCMC methods on implicitly defined manifolds
Project-URL: Homepage, https://github.com/krzysztofrusek/jax_chmc
Author-email: Krzysztof Rusek <krusek@agh.edu.pl>
License:                                  Apache License
License-File: LICENSE
Keywords: MCMC,distribution,jax
Classifier: Development Status :: 3 - Alpha
Classifier: Intended Audience :: Developers
Classifier: Intended Audience :: Financial and Insurance Industry
Classifier: Intended Audience :: Information Technology
Classifier: Intended Audience :: Science/Research
Classifier: License :: OSI Approved :: Apache Software License
Classifier: Natural Language :: English
Classifier: Programming Language :: Python :: 3
Classifier: Topic :: Scientific/Engineering :: Information Analysis
Classifier: Topic :: Scientific/Engineering :: Mathematics
Requires-Python: >=3.10
Requires-Dist: diffrax>=0.5.0
Requires-Dist: jax>=0.4.25
Requires-Dist: jaxtyping>=0.2.28
Requires-Dist: tensorflow-probability[jax]>=0.23.0
